althra/__about__.py
althra/__init__.py
althra/core/__init__.py
althra/core/config/__init__.py
althra/core/config/app.py
althra/core/config/project.py
althra/core/config/connections/__init__.py
althra/core/config/connections/postgres.py
althra/core/config/connections/sqlite.py
althra_core-0.0.1.dist-info/METADATA
althra_core-0.0.1.dist-info/WHEEL
althra_core-0.0.1.dist-info/licenses/LICENSE.txt
althra_core-0.0.1.dist-info/RECORD
