Metadata-Version: 2.1
Name: althra-core
Version: 0.0.1
Project-URL: Documentation, https://github.com/unknown/althra-core#readme
Project-URL: Issues, https://github.com/unknown/althra-core/issues
Project-URL: Source, https://github.com/unknown/althra-core
Author-email: Julien Kieffer <julien@mefa.tech>
License-Expression: BSD-3-Clause
License-File: LICENSE.txt
Classifier: Development Status :: 4 - Beta
Classifier: Programming Language :: Python
Classifier: Programming Language :: Python :: 3.7
Classifier: Programming Language :: Python :: 3.8
Classifier: Programming Language :: Python :: 3.9
Classifier: Programming Language :: Python :: 3.10
Classifier: Programming Language :: Python :: 3.11
Classifier: Programming Language :: Python :: Implementation :: CPython
Classifier: Programming Language :: Python :: Implementation :: PyPy
Requires-Python: >=3.7
Requires-Dist: pydantic
Requires-Dist: pydantic-settings
